setup.py
HTTPS_filesystem/sync_client.py
HTTPS_filesystem/sync_server.py
HTTPS_filesystem.egg-info/PKG-INFO
HTTPS_filesystem.egg-info/SOURCES.txt
HTTPS_filesystem.egg-info/dependency_links.txt
HTTPS_filesystem.egg-info/not-zip-safe
HTTPS_filesystem.egg-info/requires.txt
HTTPS_filesystem.egg-info/top_level.txt