Metadata-Version: 1.0
Name: HTTPS-filesystem
Version: 1.1
Summary: A file sync utility that uses https to provide an abstraction of a local filesystem "mounted" on a remote host
Home-page: https://github.com/aduriseti/FileSync_2_stage_authentication.git
Author: Amal Duriseti
Author-email: aduriseti@gmail.com
License: MIT
Platform: UNKNOWN
